mindmap_mcp_server/__init__.py
mindmap_mcp_server/server.py
mseep_mindmap_mcp_server-0.1.5.dist-info/METADATA
mseep_mindmap_mcp_server-0.1.5.dist-info/WHEEL
mseep_mindmap_mcp_server-0.1.5.dist-info/entry_points.txt
mseep_mindmap_mcp_server-0.1.5.dist-info/licenses/LICENSE
mseep_mindmap_mcp_server-0.1.5.dist-info/RECORD
